AUTHORS.rst
CONTRIBUTING.rst
HISTORY.rst
LICENSE
MANIFEST.in
README.rst
setup.cfg
setup.py
docs/Makefile
docs/authors.rst
docs/conf.py
docs/contributing.rst
docs/history.rst
docs/index.rst
docs/installation.rst
docs/make.bat
docs/readme.rst
docs/usage.rst
packyou/__init__.py
packyou.egg-info/PKG-INFO
packyou.egg-info/SOURCES.txt
packyou.egg-info/dependency_links.txt
packyou.egg-info/not-zip-safe
packyou.egg-info/requires.txt
packyou.egg-info/top_level.txt
packyou/github/__init__.py
packyou/github/llazzaro/__init__.py
packyou/github/llazzaro/test_scripts/__init__.py
packyou/github/llazzaro/test_scripts/test.py
tests/__init__.py
tests/test_github_importer.py
tests/test_import.py