Metadata-Version: 1.1
Name: packyou
Version: 0.1.5
Summary: Downloads or clones a python project from github and allows to import it from anywhere. Very useful when the repo is not a package
Home-page: https://github.com/llazzaro/packyou
Author: Leonardo Lazzaro
Author-email: llazzaro@dc.uba.ar
License: MIT license
Keywords: packyou
Platform: UNKNOWN
Classifier: Development Status :: 2 - Pre-Alpha
Classifier: Intended Audience :: Developers
Classifier: License :: OSI Approved :: MIT License
Classifier: Natural Language :: English
Classifier: Programming Language :: Python :: 2
Classifier: Programming Language :: Python :: 2.6
Classifier: Programming Language :: Python :: 2.7
Classifier: Programming Language :: Python :: 3
Classifier: Programming Language :: Python :: 3.3
Classifier: Programming Language :: Python :: 3.4
Classifier: Programming Language :: Python :: 3.5
